local_mcp_server/__init__.py
local_mcp_server/dto/__init__.py
local_mcp_server/dto/dto.py
local_mcp_server/dto/dto_timeline.py
local_mcp_server/flowlens_mcp/__init__.py
local_mcp_server/flowlens_mcp/server_instance.py
local_mcp_server/flowlens_mcp/tools.py
local_mcp_server/models/__init__.py
local_mcp_server/models/enums.py
local_mcp_server/server.py
local_mcp_server/service/__init__.py
local_mcp_server/service/flow_lens.py
local_mcp_server/service/timeline.py
local_mcp_server/utils/__init__.py
local_mcp_server/utils/flow_registry.py
local_mcp_server/utils/http_request.py
local_mcp_server/utils/logger_setup.py
local_mcp_server/utils/settings.py
local_mcp_server/utils/timeline/__init__.py
local_mcp_server/utils/timeline/loader.py
local_mcp_server/utils/timeline/processor.py
local_mcp_server/utils/timeline/registry.py
local_mcp_server/utils/video/__init__.py
local_mcp_server/utils/video/handler.py
magentic_mcp_server-0.1.17.dist-info/METADATA
magentic_mcp_server-0.1.17.dist-info/WHEEL
magentic_mcp_server-0.1.17.dist-info/entry_points.txt
magentic_mcp_server-0.1.17.dist-info/RECORD
