Metadata-Version: 2.1
Name: magentic-mcp-server
Version: 0.1.17
Summary: Local MCP server shim for development
License: MIT
Author: magentic
Author-email: devnull@example.com
Requires-Python: >=3.10,<4.0
Classifier: License :: OSI Approved :: MIT License
Classifier: Programming Language :: Python :: 3
Classifier: Programming Language :: Python :: 3.10
Classifier: Programming Language :: Python :: 3.11
Classifier: Programming Language :: Python :: 3.12
Classifier: Programming Language :: Python :: 3.13
Requires-Dist: aiofiles (>=24.1.0,<25.0.0)
Requires-Dist: aiohttp (>=3.12.15,<4.0.0)
Requires-Dist: build (>=1.3.0,<2.0.0)
Requires-Dist: fastmcp
Requires-Dist: opencv-python (>=4.12.0.88,<5.0.0.0)
Requires-Dist: pipx (>=1.8.0,<2.0.0)
Requires-Dist: starlette
Requires-Dist: twine (>=6.2.0,<7.0.0)
